tsetmc/__init__.py
tsetmc/dataset/__init__.py
tsetmc/dataset/dataset.csv
tsetmc/dataset/~dataset copy.csv
tsetmc/docs.py
tsetmc/funds.py
tsetmc/general.py
tsetmc/indices.py
tsetmc/instruments.py
tsetmc/market_watch.py
tsetmc/~last_response.html
tsetmc-3.0.0.dist-info/WHEEL
tsetmc-3.0.0.dist-info/METADATA
tsetmc-3.0.0.dist-info/RECORD
