Metadata-Version: 2.3
Name: tsetmc
Version: 3.0.0
Summary: a library to retrieve data from tsetmc.com website
Keywords: tsetmc,client
Author: 5j9
Author-email: 5j9 <5j9@users.noreply.github.com>
License: GNU General Public License v3 (GPLv3)
Classifier: License :: OSI Approved :: GNU General Public License v3 (GPLv3)
Classifier: Programming Language :: Python :: 3.12
Requires-Dist: aiohutils>=0.22.4
Requires-Dist: jdatetime
Requires-Dist: lxml
Requires-Dist: numpy
Requires-Dist: pandas>=3.0.0
Requires-Dist: pyarrow
Requires-Python: >=3.13
Project-URL: Homepage, https://github.com/5j9/tsetmc
